twitter_mood/__init__.py
twitter_mood/mood_gatherer.py
twitter_mood-0.0.8.dist-info/METADATA
twitter_mood-0.0.8.dist-info/RECORD
twitter_mood-0.0.8.dist-info/WHEEL
twitter_mood-0.0.8.dist-info/entry_points.txt
twitter_mood-0.0.8.dist-info/top_level.txt
